package/__init__.py
griddic_dummy_package-0.0.1.dist-info/METADATA
griddic_dummy_package-0.0.1.dist-info/WHEEL
griddic_dummy_package-0.0.1.dist-info/top_level.txt
griddic_dummy_package-0.0.1.dist-info/RECORD
